eparse/__init__.py
eparse/cli.py
eparse/core.py
eparse/interfaces.py
eparse/migrations.py
eparse/contrib/__init__.py
eparse/contrib/unstructured/__init__.py
eparse/contrib/unstructured/partition.py
eparse/contrib/unstructured/xlsx.py
eparse-0.7.3.dist-info/AUTHORS.rst
eparse-0.7.3.dist-info/LICENSE
eparse-0.7.3.dist-info/METADATA
eparse-0.7.3.dist-info/WHEEL
eparse-0.7.3.dist-info/entry_points.txt
eparse-0.7.3.dist-info/top_level.txt
eparse-0.7.3.dist-info/RECORD
