Metadata-Version: 2.1
Name: eparse
Version: 0.7.3
Summary: Excel spreadsheet crawler and table parser for data discovery, extraction, and querying
Home-page: https://github.com/ChrisPappalardo/eparse
Author: Chris Pappalardo
Author-email: cpappala@gmail.com
License: MIT license
Keywords: eparse
Classifier: Development Status :: 4 - Beta
Classifier: Intended Audience :: Developers
Classifier: Intended Audience :: End Users/Desktop
Classifier: License :: OSI Approved :: MIT License
Classifier: Natural Language :: English
Classifier: Programming Language :: Python :: 3
Classifier: Programming Language :: Python :: 3.8
Classifier: Programming Language :: Python :: 3.9
Classifier: Programming Language :: Python :: 3.10
Classifier: Programming Language :: Python :: 3.11
Requires-Python: >=3.8
License-File: LICENSE
License-File: AUTHORS.rst
Requires-Dist: click (>=8.0.0)
Requires-Dist: openpyxl (>=3.0.0)
Requires-Dist: lxml (>=4.9.3)
Requires-Dist: pandas (>=2.0.0)
Requires-Dist: peewee (>=3.16.0)
Requires-Dist: unstructured (>=0.8.5)
